eci_as_sandbox-0.2.2.dist-info/METADATA
eci_as_sandbox-0.2.2.dist-info/WHEEL
eci_as_sandbox-0.2.2.dist-info/entry_points.txt
eci_as_sandbox/__init__.py
eci_as_sandbox/_async/__init__.py
eci_as_sandbox/_async/client.py
eci_as_sandbox/_async/sandbox.py
eci_as_sandbox/_common/__init__.py
eci_as_sandbox/_common/config.py
eci_as_sandbox/_common/exceptions.py
eci_as_sandbox/_common/logger.py
eci_as_sandbox/_common/models.py
eci_as_sandbox/_common/ws.py
eci_as_sandbox/_sync/__init__.py
eci_as_sandbox/_sync/client.py
eci_as_sandbox/_sync/sandbox.py
eci_as_sandbox-0.2.2.dist-info/RECORD
