Metadata-Version: 2.1
Name: eci-as-sandbox
Version: 0.2.2
Summary: ECI-backed sandbox manager with an Agent interface.
License: Apache-2.0
Project-URL: Homepage, https://github.com/AndersonBY/eci-as-sandbox
Project-URL: Repository, https://github.com/AndersonBY/eci-as-sandbox
Project-URL: Issues, https://github.com/AndersonBY/eci-as-sandbox/issues
Requires-Python: >=3.9
Requires-Dist: alibabacloud-eci20180808>=2.0.8
Requires-Dist: python-dotenv>=1.0.0
Requires-Dist: websocket-client>=1.9.0
Requires-Dist: websockets>=15.0.1
